[
"03.13.32.870176",
{"position":{"x":-0.5237393379211426,"y":0.0010050013661384583,"z":-0.4184662103652954},"type":"target"},
{"position":{"x":-0.6213419437408447,"y":0.0010050013661384583,"z":-0.13439804315567017},"type":"target"},
{"position":{"x":0.0,"y":0.0,"z":0.0},"type":"0"},
{"position":{"x":0.0,"y":0.0,"z":0.0},"type":"0"},
{"position":{"x":0.0,"y":0.0,"z":0.0},"type":"0"},
{"position":{"x":0.0,"y":0.0,"z":0.0},"type":"0"},
{"position":{"x":0.0,"y":0.0,"z":0.0},"type":"0"},
{"position":{"x":0.0,"y":0.0,"z":0.0},"type":"0"},
{"position":{"x":0.0,"y":0.0,"z":0.0},"type":"0"},
{"position":{"x":0.0,"y":0.0,"z":0.0},"type":"0"},
{"position":{"x":0.8272964954376221,"y":0.0010050013661384583,"z":-0.19928312301635743},"type":"target"},
{"position":{"x":0.6692030429840088,"y":0.0010050013661384583,"z":-0.5183323621749878},"type":"target"},
{"position":{"x":0.0,"y":0.0,"z":0.0},"type":"0"},
{"position":{"x":0.0,"y":0.0,"z":0.0},"type":"0"},
{"position":{"x":0.0,"y":0.0,"z":0.0},"type":"0"},
{"position":{"x":0.0,"y":0.0,"z":0.0},"type":"0"},
{"position":{"x":0.0,"y":0.0,"z":0.0},"type":"0"},
{"position":{"x":0.0,"y":0.0,"z":0.0},"type":"0"},
{"position":{"x":0.0,"y":0.0,"z":0.0},"type":"0"},
{"position":{"x":0.0,"y":0.0,"z":0.0},"type":"0"},
{"position":{"x":1.783937931060791,"y":0.0010050013661384583,"z":-0.18876630067825318},"type":"target"},
{"position":{"x":1.9294440746307374,"y":0.0010050013661384583,"z":-0.7624952793121338},"type":"target"},
{"position":{"x":0.0,"y":0.0,"z":0.0},"type":"0"},
{"position":{"x":0.0,"y":0.0,"z":0.0},"type":"0"},
{"position":{"x":0.0,"y":0.0,"z":0.0},"type":"0"},
{"position":{"x":0.0,"y":0.0,"z":0.0},"type":"0"},
{"position":{"x":0.0,"y":0.0,"z":0.0},"type":"0"},
{"position":{"x":0.0,"y":0.0,"z":0.0},"type":"0"},
{"position":{"x":0.0,"y":0.0,"z":0.0},"type":"0"},
{"position":{"x":0.0,"y":0.0,"z":0.0},"type":"0"},
{"position":{"x":3.1352035999298097,"y":0.0010050013661384583,"z":-0.7821352481842041},"type":"target"},
{"position":{"x":3.4555134773254396,"y":0.0010050013661384583,"z":-0.6410039663314819},"type":"target"},
{"position":{"x":0.0,"y":0.0,"z":0.0},"type":"0"},
{"position":{"x":0.0,"y":0.0,"z":0.0},"type":"0"},
{"position":{"x":0.0,"y":0.0,"z":0.0},"type":"0"},
{"position":{"x":0.0,"y":0.0,"z":0.0},"type":"0"},
{"position":{"x":0.0,"y":0.0,"z":0.0},"type":"0"},
{"position":{"x":0.0,"y":0.0,"z":0.0},"type":"0"},
{"position":{"x":0.0,"y":0.0,"z":0.0},"type":"0"},
{"position":{"x":0.0,"y":0.0,"z":0.0},"type":"0"},
{"position":{"x":4.768548965454102,"y":0.0010050013661384583,"z":-0.5864130258560181},"type":"target"},
{"position":{"x":5.105015754699707,"y":0.0010050013661384583,"z":-0.27618926763534548},"type":"target"},
{"position":{"x":0.0,"y":0.0,"z":0.0},"type":"0"},
{"position":{"x":0.0,"y":0.0,"z":0.0},"type":"0"},
{"position":{"x":0.0,"y":0.0,"z":0.0},"type":"0"},
{"position":{"x":0.0,"y":0.0,"z":0.0},"type":"0"},
{"position":{"x":0.0,"y":0.0,"z":0.0},"type":"0"},
{"position":{"x":0.0,"y":0.0,"z":0.0},"type":"0"},
{"position":{"x":0.0,"y":0.0,"z":0.0},"type":"0"},
{"position":{"x":0.0,"y":0.0,"z":0.0},"type":"0"},
{"position":{"x":7.506545543670654,"y":0.0010050013661384583,"z":-0.8934547901153565},"type":"target"},
{"position":{"x":7.336331844329834,"y":0.0010050013661384583,"z":-0.32578760385513308},"type":"target"},
{"position":{"x":0.0,"y":0.0,"z":0.0},"type":"0"},
{"position":{"x":0.0,"y":0.0,"z":0.0},"type":"0"},
{"position":{"x":0.0,"y":0.0,"z":0.0},"type":"0"},
{"position":{"x":0.0,"y":0.0,"z":0.0},"type":"0"},
{"position":{"x":0.0,"y":0.0,"z":0.0},"type":"0"},
{"position":{"x":0.0,"y":0.0,"z":0.0},"type":"0"},
{"position":{"x":0.0,"y":0.0,"z":0.0},"type":"0"},
{"position":{"x":0.0,"y":0.0,"z":0.0},"type":"0"},
{"position":{"x":0.8337745666503906,"y":0.0010050013661384583,"z":0.46744799613952639},"type":"target"},
{"position":{"x":1.0364611148834229,"y":0.0010050013661384583,"z":0.10108481347560883},"type":"target"},
{"position":{"x":0.0,"y":0.0,"z":0.0},"type":"0"},
{"position":{"x":0.0,"y":0.0,"z":0.0},"type":"0"},
{"position":{"x":0.0,"y":0.0,"z":0.0},"type":"0"},
{"position":{"x":0.0,"y":0.0,"z":0.0},"type":"0"},
{"position":{"x":0.0,"y":0.0,"z":0.0},"type":"0"},
{"position":{"x":0.0,"y":0.0,"z":0.0},"type":"0"},
{"position":{"x":0.0,"y":0.0,"z":0.0},"type":"0"},
{"position":{"x":0.0,"y":0.0,"z":0.0},"type":"0"},
{"position":{"x":4.993305683135986,"y":0.0010050013661384583,"z":0.6222837567329407},"type":"target"},
{"position":{"x":4.770112991333008,"y":0.0010050013661384583,"z":0.41985878348350527},"type":"target"},
{"position":{"x":0.0,"y":0.0,"z":0.0},"type":"0"},
{"position":{"x":0.0,"y":0.0,"z":0.0},"type":"0"},
{"position":{"x":0.0,"y":0.0,"z":0.0},"type":"0"},
{"position":{"x":0.0,"y":0.0,"z":0.0},"type":"0"},
{"position":{"x":0.0,"y":0.0,"z":0.0},"type":"0"},
{"position":{"x":0.0,"y":0.0,"z":0.0},"type":"0"},
{"position":{"x":0.0,"y":0.0,"z":0.0},"type":"0"},
{"position":{"x":0.0,"y":0.0,"z":0.0},"type":"0"}
]
